sigproSS/__init__.py
sigproSS/signatures_optimizer.py
sigproSS/spss.py
sigproSS/spss_pcwag.py
sigproSS/input/.DS_Store
sigproSS/input/20181108_Signature_Rules.xml
sigproSS/input/Signature_Rules_Schema.xsd
sigproSS/input/csv_example192.csv
sigproSS/input/csv_example96.csv
sigproSS/input/exomeSignatures.txt
sigproSS/input/genomeSignatures.txt
sigproSS/input/sigProfiler_DBS_signatures.csv
sigproSS/input/sigProfiler_ID_signatures.csv
sigproSS/input/sigProfiler_SBS_signatures.csv
sigproSS/input/sigProfiler_SBS_signatures_2018_03_28.csv
sigproSS/input/sigProfiler_TSB_signatures.csv
sigproSS/input/signaturesSet.txt
sigproSS/input/vcf/test_example_1.vcf
sigproSS/input/vcf/test_example_10.vcf
sigproSS/input/vcf/test_example_2.vcf
sigproSS/input/vcf/test_example_3.vcf
sigproSS/input/vcf/test_example_4.vcf
sigproSS/input/vcf/test_example_5.vcf
sigproSS/input/vcf/test_example_6.vcf
sigproSS/input/vcf/test_example_7.vcf
sigproSS/input/vcf/test_example_8.vcf
sigproSS/input/vcf/test_example_9.vcf
sigproSS-0.0.0.27.dist-info/METADATA
sigproSS-0.0.0.27.dist-info/WHEEL
sigproSS-0.0.0.27.dist-info/top_level.txt
sigproSS-0.0.0.27.dist-info/RECORD
